filers2/__init__.py
filers2/filers2_style.kv
filers2/main.py
filers2/run_app.py
filers2/utils.py
filers2/compression/__init__.py
filers2/compression/compression_style.kv
filers2/recording/__init__.py
filers2/recording/player_style.kv
filers2/tests/__init__.py
filers2/tests/test_recording.py
filers2-0.2.0.dist-info/LICENSE
filers2-0.2.0.dist-info/METADATA
filers2-0.2.0.dist-info/WHEEL
filers2-0.2.0.dist-info/entry_points.txt
filers2-0.2.0.dist-info/top_level.txt
filers2-0.2.0.dist-info/RECORD
