Metadata-Version: 2.1
Name: filers2
Version: 0.2.0
Summary: Video tools for recording experiments.
Home-page: https://github.com/matham/filers2
Author: Matthew Einhorn
Author-email: matt@einhorn.dev
License: MIT
Project-URL: Bug Reports, https://github.com/matham/filers2/issues
Project-URL: Source, https://github.com/matham/filers2
Classifier: Development Status :: 4 - Beta
Classifier: License :: OSI Approved :: MIT License
Classifier: Programming Language :: Python :: 3.7
Classifier: Programming Language :: Python :: 3.8
Classifier: Programming Language :: Python :: 3.9
Classifier: Programming Language :: Python :: 3.10
License-File: LICENSE
Requires-Dist: base-kivy-app (~=0.1.1)
Requires-Dist: ffpyplayer
Requires-Dist: kivy (~=2.1.0)
Requires-Dist: psutil
Requires-Dist: cpl-media (~=0.1.2)
Requires-Dist: tree-config (~=0.1.1)
Provides-Extra: dev
Requires-Dist: pytest (>=3.6) ; extra == 'dev'
Requires-Dist: pytest-cov ; extra == 'dev'
Requires-Dist: flake8 ; extra == 'dev'
Requires-Dist: sphinx-rtd-theme ; extra == 'dev'
Requires-Dist: coveralls ; extra == 'dev'
Requires-Dist: trio ; extra == 'dev'
Requires-Dist: pytest-trio ; extra == 'dev'
Requires-Dist: pyinstaller ; extra == 'dev'
